storjnode/__init__.py
storjnode/common.py
storjnode/config.py
storjnode/encryptedio.py
storjnode/log.py
storjnode/util.py
storjnode/version.py
storjnode/network/__init__.py
storjnode/network/file_handshake.py
storjnode/network/file_transfer.py
storjnode/network/map.py
storjnode/network/message.py
storjnode/network/monitor.py
storjnode/network/node.py
storjnode/network/process_transfers.py
storjnode/network/protocol.py
storjnode/network/repeat_relay.py
storjnode/network/server.py
storjnode/network/bandwidth/__init__.py
storjnode/network/bandwidth/constants.py
storjnode/network/bandwidth/do_requests.py
storjnode/network/bandwidth/do_responses.py
storjnode/network/bandwidth/limit.py
storjnode/network/bandwidth/test.py
storjnode/network/messages/__init__.py
storjnode/network/messages/base.py
storjnode/network/messages/info.py
storjnode/network/messages/peers.py
storjnode/network/messages/signal.py
storjnode/storage/__init__.py
storjnode/storage/manager.py
storjnode/storage/shard.py
storjnode-0.0.21.data/scripts/storjnode
storjnode-0.0.21.dist-info/DESCRIPTION.rst
storjnode-0.0.21.dist-info/METADATA
storjnode-0.0.21.dist-info/RECORD
storjnode-0.0.21.dist-info/WHEEL
storjnode-0.0.21.dist-info/metadata.json
storjnode-0.0.21.dist-info/top_level.txt
tests/__init__.py
tests/config.py
tests/encryptedio.py
tests/util.py
tests/network/__init__.py
tests/network/bandwidth_test.py
tests/network/file_handshake.py
tests/network/file_transfer.py
tests/network/message.py
tests/network/node.py
tests/network/process_transfers.py
tests/network/queued_file_transfer.py
tests/network/server_test.py
tests/network/bandwidth/__init__.py
tests/network/bandwidth/do_requests.py
tests/network/bandwidth/do_responses.py
tests/network/bandwidth/limit.py
tests/network/bandwidth/test.py
tests/network/messages/__init__.py
tests/network/messages/base.py
tests/network/messages/info.py
tests/network/messages/peers.py
tests/network/messages/signal.py
tests/storage/__init__.py
tests/storage/manager.py
tests/storage/shard.py
