Metadata-Version: 2.0
Name: storjnode
Version: 0.0.21
Summary: Low level storj protocol reference implementation.
Home-page: http://storj.io
Author: Shawn Wilkinson
Author-email: shawn+storjnode@storj.io
License: MIT
Keywords: storj,reference,protocol,DHT
Platform: UNKNOWN
Classifier: Development Status :: 2 - Pre-Alpha
Classifier: Intended Audience :: Developers
Classifier: License :: OSI Approved :: MIT License
Classifier: Operating System :: OS Independent
Classifier: Programming Language :: Python
Classifier: Programming Language :: Python :: 2
Classifier: Programming Language :: Python :: 2.7
Classifier: Programming Language :: Python :: 3
Classifier: Programming Language :: Python :: 3.3
Classifier: Programming Language :: Python :: 3.4
Classifier: Topic :: Software Development :: Libraries :: Python Modules
Requires-Dist: btctxstore (>=4.6.1)
Requires-Dist: crochet (>=1.4.0)
Requires-Dist: ipaddress (>=1.0.14)
Requires-Dist: kademlia (>=0.5)
Requires-Dist: netifaces (>=0.10.4)
Requires-Dist: ntplib (>=0.3.3)
Requires-Dist: psutil (>=3.2.2)
Requires-Dist: pycrypto (>=2.6.1)
Requires-Dist: pyp2p (>=0.4.5)
Requires-Dist: requests (>=2.8.1)
Requires-Dist: twisted (>=15.4.0)
